jaxpy/__init__.py
jaxpy/_preprocess.py
jaxpy/_random_jax.py
jaxpy/_random_jax_overloads.py
jaxpy/_seed.py
jaxpy/jaxpy_main.py
jaxpy/random.py
jaxpy-0.0.0.dist-info/METADATA
jaxpy-0.0.0.dist-info/WHEEL
jaxpy-0.0.0.dist-info/entry_points.txt
jaxpy-0.0.0.dist-info/RECORD
