Metadata-Version: 2.4
Name: jaxpy
Version: 0.0.0
Summary: Add your description here
Author-email: Bernardo Esteves <24633851+esteveste@users.noreply.github.com>
Requires-Python: >=3.10
Requires-Dist: flax
Requires-Dist: jax
